{
    "description": "De parkeervakken in de stad worden hier als een lijst getoond.",
    "organization_name": "Gemeente Amsterdam",
    "service_name": "Parkeervakken",
    "api_type": "rest_json",
    "api_authentication": "none",
    "environments": [
        {
            "name": "production",
            "api_url": "https://api.data.amsterdam.nl/v1/parkeervakken/parkeervakken/",
            "specification_url": "https://api.data.amsterdam.nl/v1/",
            "documentation_url": "https://api.data.amsterdam.nl/parkeervakken/"
        }
    ],
    "contact": {
        "email": "datapunt@amsterdam.nl",
        "phone": "",
        "url": ""
    },
    "is_reference_implementation": false,
    "terms_of_use": {
        "government_only": false,
        "pay_per_use": false,
        "uptime_guarantee": 0,
        "support_response_time": null
    }
}
