{
    "description": "Zoek naar een bedrijf, vind relevante data in het Handelsregister",
    "organization_name": "Kamers van Koophandel",
    "service_name": "KvK Search",
    "api_type": "rest_json",
    "api_authentication": "unknown",
    "tags": [
        "handelsregister",
        "koophandel",
        "bedrijveninformatie"
    ],
    "environments": [{
        "name": "production",
        "api_url": "https://api.kvk.nl:443",
        "specification_url": "",
        "documentation_url": "https://developers.kvk.nl/documentation/search-v2"
    }],
    "contact": {
        "email": "",
        "phone": "",
        "fax": "",
        "chat": "",
        "url": "https://developers.kvk.nl"
    },
    "is_reference_implementation": false,
    "terms_of_use": {
        "government_only": false,
        "pay_per_use": true,
        "uptime_guarantee": 90,
        "support_response_time": ""
    }
}
